vaspgibbs/__init__.py
vaspgibbs/thermo.py
vaspgibbs/utils.py
vaspgibbs-0.2.3.data/scripts/vasp_gibbs
vaspgibbs-0.2.3.dist-info/METADATA
vaspgibbs-0.2.3.dist-info/WHEEL
vaspgibbs-0.2.3.dist-info/top_level.txt
vaspgibbs-0.2.3.dist-info/RECORD
