Metadata-Version: 2.2
Name: VaspGibbs
Version: 0.2.3
Summary: A simplified way to get Gibbs free energy from Vasp calculations
Home-page: https://github.com/ftherrien/VaspGibbs
Author: Felix Therrien
Author-email: felix.therrien@gmail.com
License: MIT
Requires-Python: >=3
Requires-Dist: numpy
Dynamic: author
Dynamic: author-email
Dynamic: home-page
Dynamic: license
Dynamic: requires-dist
Dynamic: requires-python
Dynamic: summary
